txtai/__init__.py
txtai/version.py
txtai/agent/__init__.py
txtai/agent/base.py
txtai/agent/factory.py
txtai/agent/model.py
txtai/agent/placeholder.py
txtai/agent/tool/__init__.py
txtai/agent/tool/embeddings.py
txtai/agent/tool/factory.py
txtai/agent/tool/function.py
txtai/ann/__init__.py
txtai/ann/base.py
txtai/ann/dense/__init__.py
txtai/ann/dense/annoy.py
txtai/ann/dense/factory.py
txtai/ann/dense/faiss.py
txtai/ann/dense/ggml.py
txtai/ann/dense/hnsw.py
txtai/ann/dense/numpy.py
txtai/ann/dense/pgvector.py
txtai/ann/dense/sqlite.py
txtai/ann/dense/torch.py
txtai/ann/sparse/__init__.py
txtai/ann/sparse/factory.py
txtai/ann/sparse/ivfsparse.py
txtai/ann/sparse/pgsparse.py
txtai/api/__init__.py
txtai/api/application.py
txtai/api/authorization.py
txtai/api/base.py
txtai/api/cluster.py
txtai/api/extension.py
txtai/api/factory.py
txtai/api/route.py
txtai/api/responses/__init__.py
txtai/api/responses/factory.py
txtai/api/responses/json.py
txtai/api/responses/messagepack.py
txtai/api/routers/__init__.py
txtai/api/routers/agent.py
txtai/api/routers/caption.py
txtai/api/routers/embeddings.py
txtai/api/routers/entity.py
txtai/api/routers/extractor.py
txtai/api/routers/labels.py
txtai/api/routers/llm.py
txtai/api/routers/objects.py
txtai/api/routers/openai.py
txtai/api/routers/rag.py
txtai/api/routers/reranker.py
txtai/api/routers/segmentation.py
txtai/api/routers/similarity.py
txtai/api/routers/summary.py
txtai/api/routers/tabular.py
txtai/api/routers/textractor.py
txtai/api/routers/texttospeech.py
txtai/api/routers/transcription.py
txtai/api/routers/translation.py
txtai/api/routers/upload.py
txtai/api/routers/workflow.py
txtai/app/__init__.py
txtai/app/base.py
txtai/archive/__init__.py
txtai/archive/base.py
txtai/archive/compress.py
txtai/archive/factory.py
txtai/archive/tar.py
txtai/archive/zip.py
txtai/cloud/__init__.py
txtai/cloud/base.py
txtai/cloud/factory.py
txtai/cloud/hub.py
txtai/cloud/storage.py
txtai/console/__init__.py
txtai/console/__main__.py
txtai-9.4.1.dist-info/LICENSE
txtai-9.4.1.dist-info/METADATA
txtai-9.4.1.dist-info/WHEEL
txtai-9.4.1.dist-info/top_level.txt
txtai-9.4.1.dist-info/RECORD
